{"summaries":[{"date":"2025-10-24","totalSeconds":840,"projects":{"exercises":827},"languages":{"c":444,"Log":15,"jsonc":368},"editors":{"Visual Studio Code":827},"os":{"Linux":827},"files":{"main.c":98,"text.c":345,"tasks.json":41,"launch.json":326,"extension-output-ms-dotnettools.vscode-dotnet-runtime-#1-.NET Install Tool":15},"branches":{},"hourlyData":[{"seconds":0},{"seconds":0},{"seconds":0},{"seconds":0},{"seconds":0},{"seconds":0},{"seconds":0},{"seconds":0},{"seconds":0},{"seconds":0},{"seconds":0},{"seconds":0},{"seconds":0},{"seconds":0},{"seconds":0},{"seconds":0},{"seconds":0},{"seconds":0},{"seconds":0},{"seconds":0},{"seconds":0},{"seconds":0},{"seconds":0},{"seconds":0}]},{"date":"2025-10-26","totalSeconds":3540,"projects":{"a4":3108,"code":8,"virtual_machine":407},"languages":{"c":3523},"editors":{"Visual Studio Code":3523},"os":{"Linux":3523},"files":{"main.c":440,"test.c":1109,"main2.c":141,"a4_skeleton.c":1832},"branches":{"master":407},"hourlyData":[{"seconds":0},{"seconds":0},{"seconds":0},{"seconds":0},{"seconds":0},{"seconds":0},{"seconds":0},{"seconds":0},{"seconds":0},{"seconds":0},{"seconds":0},{"seconds":0},{"seconds":0},{"seconds":0},{"seconds":0},{"seconds":0},{"seconds":0},{"seconds":0},{"seconds":0},{"seconds":0},{"seconds":0},{"seconds":0},{"seconds":0},{"seconds":0}]},{"date":"2025-10-28","totalSeconds":660,"projects":{"a4":12,"cis1300":621},"languages":{"c":634},"editors":{"Visual Studio Code":634},"os":{"Linux":634},"files":{"q8.c":573,"a4_skeleton.c":12,"a3_1365208_final.c":48},"branches":{},"hourlyData":[{"seconds":0},{"seconds":0},{"seconds":0},{"seconds":0},{"seconds":0},{"seconds":0},{"seconds":0},{"seconds":0},{"seconds":0},{"seconds":0},{"seconds":0},{"seconds":0},{"seconds":0},{"seconds":0},{"seconds":0},{"seconds":0},{"seconds":0},{"seconds":0},{"seconds":0},{"seconds":0},{"seconds":0},{"seconds":0},{"seconds":0},{"seconds":0}]}],"offsetSeconds":0}